{
    "url": "https://www.cnnbrasil.com.br/esportes/futebol/santos/desfalcando-o-santos-no-brasileirao-neymar-ironiza-gramado-nas-redes/",
    "titulo": "Desfalcando o Santos no Brasileirão, Neymar ironiza gramado nas redes",
    "subtitulo": "Atacante comentou nas redes sociais durante duelo contra o Athletico-PR, em Curitiba",
    "categoria": "Santos",
    "data_publicacao": "2026-02-12T19:31:18-03:00",
    "imagem": "https://admin.cnnbrasil.com.br/wp-content/uploads/sites/12/2025/12/Neymar-e1764852853973.jpeg?w=1080&h=608&crop=1",
    "corpo": "Neymar usou as redes sociais para comentar o gramado sintético da Arena da Baixada durante a partida entre Athletico-PR e Santos, nesta quinta-feira (12), pela terceira rodada do Campeonato Brasileiro.\nO jogador não foi relacionado para o confronto.\n\nEm publicação no X (antigo Twitter), o camisa 10 escreveu: “Praticar futebol nesse campo é quase impossível ”.\n\nPraticar futebol nesse campo é quase impossível 😂😂\nCapxSan\n— Neymar Jr (@neymarjr) February 12, 2026\n\nO meia-atacante segue fora por conta da cautela do clube em atuar em gramados sintéticos.\nDentro de campo, o jogo segue empatado em 1 a 1 ainda no primeiro tempo. Julimar abriu o placar para o Athletico-PR em cobrança de pênalti, e Thaciano deixou tudo igual para o Santos.\nhttps://www.youtube.com/watch?v=NWMrE4DY-sA&amp;list=PLk2Vxu2ZpUH2hZxQOjpMeQHPqj4Ep8l0G&amp;index=22\nO Peixe busca a primeira vitória na Série A.\nA equipe soma um ponto após derrota para a Chapecoense e empate contra o São Paulo. Além de Neymar, o técnico também não conta com Gabigol, Adonis Frías, Zé Rafael e Willian Arão.\nA partida acontece na Arena da Baixada, em Curitiba. O Athletico-PR tem um jogo a menos na competição por causa da disputa da Supercopa do Brasil."
}