{
    "url": "https://www.cnnbrasil.com.br/esportes/futebol/santos/santos-formaliza-proposta-por-zagueiro-do-racing-saiba-detalhes/",
    "titulo": "Santos formaliza proposta por zagueiro do Racing; saiba detalhes",
    "subtitulo": "Diretoria do Peixe conta com desejo do jogador para concretizar a transferência",
    "categoria": "Santos",
    "data_publicacao": "2026-02-13T20:19:56-03:00",
    "imagem": "https://admin.cnnbrasil.com.br/wp-content/uploads/sites/12/2026/02/dicesar-racing-e1771024056849.jpg?w=1200&h=630&crop=1",
    "corpo": "O Santos formalizou nesta sexta-feira (13) uma proposta de empréstimo com obrigação de compra pelo zagueiro Marco Di Cesare, do Racing, da Argentina.\nAlexandre Mattos, diretor de futebol, entrou em contato com a diretoria do clube argentino e com o estafe do atleta. A Itatiaia apurou que o dirigente do Peixe está confiante em um desfecho positivo, especialmente pela vontade do jogador.\nO Santos, porém, adota cautela em razão de negociações recentes envolvendo clubes argentinos. O Racing pode, por exemplo, exigir garantias bancárias, o que atrasaria a condução do negócio. O empréstimo seria pago.\n\nVojvoda aprova contratação\nDi Cesare foi avaliado positivamente pelo técnico Juan Pablo Vojvoda. O treinador conta com a chegada do defensor, sobretudo pelas poucas opções disponíveis no setor.\nA reportagem apurou ainda que o Santos pretende contratar, até o fim da janela de transferências, dois zagueiros e um volante. Essas são as prioridades do clube, que atravessa um momento de instabilidade dentro de campo, com resultados negativos no Campeonato Paulista e no Brasileiro.\n&nbsp;"
}