{
    "url": "https://www.cnnbrasil.com.br/esportes/futebol/botafogo/edenilson-marca-botafogo-vence-bangu-e-conquista-taca-rio-veja-ranking/",
    "titulo": "Edenílson marca, Botafogo vence Bangu e conquista Taça Rio; veja ranking",
    "subtitulo": "Glorioso chegou ao décimo troféu da competição na história\r\n",
    "categoria": "Botafogo",
    "data_publicacao": "2026-03-07T20:49:46-03:00",
    "imagem": "https://admin.cnnbrasil.com.br/wp-content/uploads/sites/12/2026/03/55135007490_544e85387a_k.jpg?w=1200&h=630&crop=1",
    "corpo": "O Botafogo é campeão da Taça Rio. O Glorioso venceu o Bangu por 3 a 1, neste sábado (7), no Nilton Santos, no Rio de Janeiro, e chegou ao décimo troféu da competição na história.\nEdenílson, Joaquín Correa e Caio Valle marcaram os gols do Botafogo, enquanto Luizinho descontou para o Alvirrubro.\nVale destacar que esta é a terceira vez que o Botafogo vence o torneio nas últimas quatro edições.\nRanking\nCom a vitória, o Botafogo subiu no ranking de campeões da Taça Rio. Agora, o Glorioso é o segundo maior vencedor do torneio, com dez títulos.\n\nDisputada desde 1982, a Taça Rio tem como maior campeão o Vasco, com 11 taças. Veja o ranking abaixo:\n\nVasco - 11 títulos\nBotafogo - 10 títulos\nFlamengo - 9 títulos\nFluminense - 4 títulos\nMadureira - 2 títulos\nBangu - 1 título\nAmericano - 1 título\nResende - 1 título\nBoavista - 1 título\nAmérica-RJ - 1 título\nVolta Redonda - 1 título\nSampaio Correa-RJ - 1 título\n\nPróximos compromissos\nO Botafogo volta a campo na próxima terça-feira (10), às 21h30 (de Brasília), quando recebe o Barcelona-EQU, pelo jogo de volta da terceira fase da fase preliminar da Copa Libertadores. O duelo será disputado no Estádio Nilton Santos. Na ida, as equipes empataram por 1 a 1.\nJá o Bangu não tem compromissos agendados para o restante da temporada 2026. A equipe do subúrbio carioca não disputará a Série D do Campeonato Brasileiro deste ano.\nhttps://stories.cnnbrasil.com.br/esportes/flamengo-domina-a-casa-veja-os-times-dos-participantes-do-bbb-26/"
}