{
    "url": "https://www.cnnbrasil.com.br/esportes/futebol/corinthians/corinthians-fernando-diniz-faz-primeiro-trabalho-sob-olhares-de-executivos/",
    "titulo": "Corinthians: Fernando Diniz faz primeiro trabalho sob olhares de executivos",
    "subtitulo": "Novo treinador se apresentou ao grupo e comandou atividade no CT sob olhares de presidente e diretor de futebol",
    "categoria": "Corinthians",
    "data_publicacao": "2026-04-07T17:14:50-03:00",
    "imagem": "https://admin.cnnbrasil.com.br/wp-content/uploads/sites/12/2026/04/diniz-e1775592825210.webp?w=659&h=371&crop=1",
    "corpo": "Começou a era Fernando Diniz no Corinthians. O treinador comandou a primeira atividade no Timão nesta terça-feira (7), no CT Joaquim Grava, em São Paulo. A atividade foi acompanhada do diretor de futebol Marcelo Paz e do presidente Osmar Stábile.\nAntes de comandar um trabalho de posse de bola no gramado, com passes, finalização e transição, Diniz se apresentou aos jogadores. O elenco alvinegro também realizou uma ativação na academia antes do trabalho em campo.\nApresentado de forma oficial nesta terça-feira (7), o Corinthians tem pressa. A equipe estreia na Copa Libertadores nesta quinta-feira (9), às 21h (de Brasília), contra o Platense-ARG, no estádio Ciudad de Vicente López, em Vicente López.\n\nMomento de pressão\nPressionado, Diniz chega para substituir Dorival. O ex-técnico foi demitido após uma sequência de nove jogos sem vitória. Ao todo, Dorival Jr. comandou o Corinthians em 63 partidas, com 25 vitórias, 19 empates e 19 derrotas — 49,7% de aproveitamento. O auxiliar Lucas Silvestre, filho do técnico, ficou à beira do campo em três jogos, com uma vitória e duas derrotas.\nTanto na segunda-feira (6), quanto na terça (7), a torcida foi até a porta do CT para realizar cobranças aos jogadores. Além das cobranças verbais, torcedores penduraram faixas na entrada do CT com mensagens como “Elenco vagabundo”, “Ou joga por amor ou joga por terror”, “Jogadores omissos” e “Acabou a paciência”.\nA principal alegação dos torcedores é de que parte do elenco fez “corpo mole” para provocar a saída do técnico Dorival Júnior, demitido após a sequência negativa."
}