{
    "url": "https://www.cnnbrasil.com.br/esportes/brasileirao/flamengo-leonardo-jardim-tem-dois-desfalques-diante-do-fluminense/",
    "titulo": "Flamengo: Leonardo Jardim tem dois desfalques diante do Fluminense",
    "categoria": "Brasileirão",
    "data": "2026-04-11 14:34:04",
    "imagem": "https://admin.cnnbrasil.com.br/wp-content/uploads/sites/12/2026/04/arrascaeta-e1775928569980.webp?w=419&h=249&crop=1",
    "descricao_imagem": "Arrascaeta reforça o Flamengo no clássico contra o Fluminense",
    "descricao": "Clássico acontece neste domingo (12), às 18h (de Brasília), no Maracanã, pela 11ª rodada do Brasileiro\r\n",
    "texto": "N/A"
}