{
    "url": "https://www.cnnbrasil.com.br/esportes/futebol/sao-paulo/torcida-do-sao-paulo-protesta-apos-derrota-e-pede-saida-de-diretor/",
    "titulo": "Torcida do São Paulo protesta após derrota e pede saída de diretor",
    "categoria": "São Paulo (Clube)",
    "data": "2026-03-22 11:05:20",
    "imagem": "https://admin.cnnbrasil.com.br/wp-content/uploads/sites/12/2026/03/Protesto-contra-o-executivo-do-Sao-Paulo-no-MorumBis.jpg?w=419&h=249&crop=1",
    "descricao_imagem": "Protesto contra o executivo do São Paulo no MorumBis",
    "descricao": "Tricolor perdeu a segunda seguida e também a liderança do Brasileirão após troca inesperada no comando técnico",
    "texto": "N/A"
}