{
    "url": "https://www.cnnbrasil.com.br/esportes/futebol/campeonato-baiano/baiano-vitoria-bate-jacuipense-e-vai-enfrentar-o-bahia-na-decisao/",
    "titulo": "Baiano: Vitória bate Jacuipense e vai enfrentar o Bahia na decisão",
    "subtitulo": "Após 1 a 1 no tempo regulamentar, Leão da Barra venceu por 4 a 2 nos pênaltis e se classificou",
    "categoria": "Campeonato Baiano",
    "data_publicacao": "2026-03-01T19:35:45-03:00",
    "imagem": "https://admin.cnnbrasil.com.br/wp-content/uploads/sites/12/2026/03/download-2.webp?w=1000&h=563&crop=1",
    "corpo": "O Vitória está na decisão do Campeonato Baiano. Na tarde deste domingo (1°), no Barradão, o Leão da Barra empatou por 1 a 1 com o Jacuipense no tempo regulamentar e conseguiu a classificação com vitória por 4 a 2 nos pênaltis.\n\nO herói da classificação foi o goleiro Lucas Arcanjo, que defendeu duas penalidades na disputa contra o Jacuipense. O Vitória teve 100% de aproveitamento.\nCom bola rolando, o Vitória abriu o placar com Renato Kayzer. Pouco depois, o time teve o volante Caíque Gonçalves expulso. Na etapa final, Pedro Henrique empatou e levou o duelo para as penalidades.\n\nA decisão do Campeonato Baiano será no próximo sábado (7), entre Bahia e Vitória. Os detalhes serão divulgados pela Federação Baiana de Futebol.\nO jogo\nO Vitória começou com tudo e logo abriu o placar diante da torcida. Após cruzamento, a bola sobrou limpa para o goleador Renato Kayzer finalizar de primeira e balançar as redes aos 3': 1 a 0.\nO Leão da Barra tentava manter o controle da partida, mas, aos 15', o árbitro foi ao VAR e expulsou o volante Caíque Gonçalves por agressão. Com isso, o Vitória ficou com um a menos no Barradão.\nAinda no primeiro tempo, o Jacuipense pressionou em busca do empate. A melhor chance foi aos 19', com o lateral-direito Hugo Moura, que acertou o travessão em belo chute.\nNa etapa final, o Vitória conseguia manter o controle da partida mesmo com um a menos. Aos 20', no entanto, Alisson Daniel recebeu pelo lado, fez boa jogada e cruzou para Pedro Henrique, livre, tocar de cabeça e empatar a partida: 1 a 1.\nDepois do gol, os dois times se preservaram e arriscaram pouco. Assim, a partida foi para os pênaltis.\nNas penalidades, o Vitória converteu os seus quatro chutes, com Renato Kayzer, Osvaldo, Cantalapiedra e Marinho. O Jacuipense perdeu dois, com duas boas defesas de Gustavo Arcanjo, em finalizações de Alisson Daniel e Flavinho. Final: 4 a 2."
}