{
    "url": "https://www.cnnbrasil.com.br/esportes/brasileirao/botafogo-vence-vasco-de-virada-com-golaco-de-matheus-martins/",
    "titulo": "Botafogo vence Vasco de virada com golaço de Matheus Martins",
    "subtitulo": "Glorioso salta para a 8ª colocação do Brasileirão com o resultado sob os olhares do novo treinador",
    "categoria": "Brasileirão",
    "data_publicacao": "2026-04-04T23:03:13-03:00",
    "imagem": "https://admin.cnnbrasil.com.br/wp-content/uploads/sites/12/2026/04/55187229132_ef8642bffa_k.jpg?w=1200&h=630&crop=1",
    "corpo": "Na Barreira do Vasco, quem se deu bem foi o Botafogo. Neste sábado (4), o Glorioso venceu o Cruzmaltino por 2 a 1 de virada, com direito a golaço de Matheus Martins, em jogo válido pela 10ª rodada do Brasileirão em São Januário.\nO resultado anima a torcida, que recebeu nesta semana o novo treinador Franclim Carvalho. O português esteve em São Januário para acompanhar a partida. A estreia está marcada para a quinta-feira (9), quando o time enfrenta o Caracas, pela Copa Sul- Americana.\n\n&nbsp;\nCom o resultado, o Alvinegro pulou para a 8ª colocação do campeonato e ultrapassou o Vasco, agora em 9º. Na próxima rodada, o Vasco pega o lanterna Remo. Já o Botafogo enfrenta o Coritiba em casa.\nO jogo\nO Botafogo começou tomando a iniciativa, usando a velocidade dos seus jogadores pelo lado do campo. Com maior posse de bola, o Vasco tinha dificuldades para levar perigo.Os erros de passe atrapalharam o Cruzmaltino, enquanto o rival apostsou nos contra-ataques.\nA chance mais perigosa do Botafogo veio após o time perder a bola no setor de ataque, em uma jogada rápida de Arthur Cabral. O jogador foi acionado em uma bola longa, ganhou da zaga do Vasco na força, e deixou para Júnior Santos. Mas o atacante pegou mal na entrada da área e mesmo com espaço para chutar, bateu mal, e Léo Jardim fez a defesa.\nO jogo era morno até os 38 minutos, quando Cuiabano acidentalmente acertou Júnior Santos no rosto na tentativa de recuperar a bola. Depois de muito bate boca em campo, o árbitro Wagner do Nascimento Magalhães resolveu apenas na conversa.\nO Botafogo conseguiu puxar mais um bom contra-ataque aos 41, mas Saldívia derrubou Matheus Martins na entrada da grande área. O jogador escapou de uma punição mais dura, ficando só com o amarelo, e na cobrança de falta, Léo Jardim socou para fora.\nNos acréscimos, Léo Jardim fez uma grande defesa em uma finalização de Matheus Martins. O camisa 11 bateu da entrada da grande área, cruzado e no alto. O goleiro vascaíno precisou se esticar para salvar a meta.\nNo início da segunda etapa, Júnior Santos e Ferraresi levaram cartões amarelos em lances seguidos ao tentar parar o ataque vascaíno. O atacante fez uma falta dura em Thiago Mendes na entrada da área, e o zagueiro, em Rojas.\nO Vasco aproveitou o momento e tentou se lançar no ataque. Tchê Tchê perdeu uma chance inacreditável ao ficar com a sobra frente a frente para o gol, e bateu para fora.\nFoi o melhor momento do Cruzmaltino na partida, e pressão logo fez efeito. Aos 15 minutos, David abriu o placar em uma jogada iniciada por Puma Rodríguez. O lateral cruzou no segundo pau rasteiro para o camisa 7, que só teve o trabalho de empurrar para o gol vazio de Raul.\nA vantagem durou pouco. Cinco minutos mais tarde, o Botafogo devolveu a pressão. Caio Roque cruzou na esquerda e encontrou Villalba, que nem precisou pular para cabecear por cima de Léo Jardim, marcando o seu primeiro gol com a camisa do Glorioso.\nO gol desorganizou o Vasco, e a virada do Botafogo veio em um golaço de Matheus Martins. O jogador bateu de fora da área e Léo Jardim pouco pôde fazer além de olhar a bola morrendo no fundo da rede.\nO Cruzmaltino não se entregou, e Spinelli, que substituiu o autor do gol David, veio à campo. O jogador assustou Léo Jardim em sua primeira finalização, um chute prensado que saiu para escanteio. Na jogada seguinte, Cuiabano bateu de longe e o argentino não conseguiu alcançar a bola para finalizar."
}