{
    "url": "https://www.cnnbrasil.com.br/esportes/futebol/selecao-brasileira/neymar-sobre-trajetoria-na-selecao-esta-chegando-ao-fim/",
    "titulo": "Neymar sobre trajetória na Seleção: \"Está chegando ao fim\"",
    "categoria": "Seleção Brasileira",
    "data": "2026-03-18 14:53:30",
    "imagem": "https://admin.cnnbrasil.com.br/wp-content/uploads/sites/12/2026/03/neymar-thiago-silva-selecao-brasileira-e1773167321682.jpg?w=419&h=249&crop=1",
    "descricao_imagem": "Thiago Silva consola Neymar após a derrota para a Croácia na Copa do Mundo de 2022",
    "descricao": "Após não ser convocado pelo técnico Carlo Ancelotti, Neymar publicou fala em seu canal",
    "texto": "N/A"
}