{
    "url": "https://www.cnnbrasil.com.br/esportes/futebol/flamengo/eu-quero-ganhar-tudo-diz-presidente-do-flamengo/",
    "titulo": "\"Eu quero ganhar tudo\", diz presidente do Flamengo",
    "subtitulo": "Bap afirma que trabalha \"o tempo inteiro\" para o Flamengo ganhar tudo",
    "categoria": "Flamengo",
    "data_publicacao": "2026-03-27T17:11:15-03:00",
    "imagem": "https://admin.cnnbrasil.com.br/wp-content/uploads/sites/12/2025/12/Bap-Flamengo-e1766574710384.jpg?w=1200&h=630&crop=1",
    "corpo": "O presidente do Flamengo, Luiz Eduardo Baptista, o Bap, afirmou nesta quinta-feira (27) que trabalha e quer que o clube rubro-negro ganhe tudo.\nEm entrevista ao MengoCast, programa da Flamengo TV, Bap confessou que é arrogante quando o assunto é ganhar títulos, mas disse que trabalha a cada minuto para isso.\n\n\nCom o comando de Bap, o Flamengo já conquistou sete títulos, inclusive o tetracampeonato da Copa Libertadores, em novembro de 2025, quando venceu o Palmeiras por 1 a 0 com gol de Danilo.\nTítulos do Flamengo com o comando de Bap\n\nLibertadores (2025): Tetra campeonato conquistado.\nBrasileirão (2025): Bicampeonato conquistado.\nCarioca (2025 e 2026): 40º e 41° título conquistado.\nSupercopa do Brasil (2025): Campeão.\nOutros: Derby das Americas e Copa Challenger"
}