{
    "url": "https://www.cnnbrasil.com.br/esportes/futebol/fluminense/veja-o-que-o-fluminense-precisa-para-conquistar-o-titulo-da-taca-guanabara/",
    "titulo": "Veja o que o Fluminense precisa para conquistar o título da Taça Guanabara",
    "subtitulo": "Tricolor é o time de melhor campanha do torneio faltando apenas uma rodada para o final da primeira fase\r\n",
    "categoria": "Fluminense",
    "data_publicacao": "2026-02-03T13:36:44-03:00",
    "imagem": "https://admin.cnnbrasil.com.br/wp-content/uploads/sites/12/2025/11/Zubeldia-e1768160841536.jpg?w=1200&h=630&crop=1",
    "corpo": "Classificado para as quartas de final do Campeonato Carioca, o Fluminense também está próximo de conquistar o título simbólico da Taça Guanabara. Com a melhor campanha da fase de grupos, o Tricolor depende de si para ficar com o troféu.\nSerá declarado campeão da Taça Guanabara quem tiver a maior pontuação entre os 12 times da primeira fase. Atualmente, o Flu lidera o Grupo A com 12 pontos. Três rivais podem tirar o título da equipe de Luís Zubeldía.\n\nCom 12 pontos, apenas o Volta Redonda pode chegar aos 13. Ou seja, se o Flu empatar com o Maricá, no domingo (8), na última rodada, o Voltaço precisa vencer o Madureira que fica na liderança e com a melhor campanha no saldo de gols. Qualquer vitória do Fluminense garante a taça.\nBotafogo e Bangu são outros que podem ter melhor campanha que o Fluminense. Mas para isso, além de vencer, precisa torcer por derrota tricolor. Os dois times somam nove pontos. o Glorioso encara o Vasco, enquanto o Alvirrubro terá o Boavista pela frente.\nCom vaga assegurada, o Tricolor já tem R$ 1 milhão garantido em premiação pela classificação às quartas de final. O Botafogo é outro matematicamente já garantido na próxima fase.\nAntes disso, o Fluminense visita o Bahia, na quinta-feira (5), às 19h (de Brasília), na Arena Fonte Nova, em Salvador, pela segunda rodada da Série A do Campeonato Brasileiro."
}