{
    "url": "https://www.cnnbrasil.com.br/esportes/futebol/campeonato-baiano/arbitro-da-final-do-campeonato-baiano-ja-foi-criticado-por-rogerio-ceni/",
    "titulo": "Árbitro da final do Campeonato Baiano já foi criticado por Rogério Ceni",
    "subtitulo": "Profissional também apitou jogo de volta da final do Baianão de 2025, conquistado pelo Tricolor\r\n",
    "categoria": "Campeonato Baiano",
    "data_publicacao": "2026-03-04T16:31:46-03:00",
    "imagem": "https://admin.cnnbrasil.com.br/wp-content/uploads/sites/12/2025/09/Ceni-Bahia.webp?w=1000&h=563&crop=1",
    "corpo": "A Federação Bahiana de Futebol (FBF) definiu, nesta quarta-feira (4), a equipe de arbitragem para a final do Campeonato Baiano entre Bahia e Vitória. A decisão será disputada em jogo único, na Arena Fonte Nova, em Salvador, neste sábado (7), às 17h (de Brasília).\nO árbitro principal será o goiano Wilton Pereira Sampaio. Aos 44 anos, ele integra o quadro da FIFA desde 2013 e acumula experiência internacional, com participações em duas Copas do Mundo.\nAo lado de Wilton estarão os assistentes Luanderson Lima dos Santos e Daniella Coutinho Pinto, ambos baianos e integrantes do quadro da FIFA. O árbitro de vídeo (VAR) será Caio Max Augusto Vieira, também da FIFA e representante do estado de Goiás.\n\nCríticas de Rogério Ceni\nCuriosamente, Wilton já foi alvo de críticas do técnico Rogério Ceni, do Bahia. Em julho de 2025, após o empate por 1 a 1 com o Fortaleza, pelo Campeonato Brasileiro, o treinador fez duras reclamações sobre a atuação da arbitragem.\nNa ocasião, o treinador tricolor contestou um suposto pênalti não marcado cometido pelo atacante Yago Pikachu no meia Cauly, no último lance da partida.\n“Uma arbitragem desastrosa, mais uma vez. Um pênalti claríssimo no final do jogo, que não foi nem revisado pelo VAR. Nesse caso, nem tanto a arbitragem, mas o VAR foi terrível. Não revisar o lance no último minuto... Nem revisaram”, declarou o treinador à época.\nVale lembrar também que Wilton apitou o jogo de volta da final do Campeonato Baiano de 2025, também disputada entre Bahia e Vitória. Na ocasião, o Bahia levantou o título após vencer a partida de ida e empatar no Barradão.\nhttps://stories.cnnbrasil.com.br/esportes/real-madrid-confirma-lesao-e-rodrygo-esta-fora-da-copa-do-mundo/\n&nbsp;"
}