{
    "url": "https://www.cnnbrasil.com.br/esportes/futebol/selecao-brasileira/brasil-x-franca-veja-gol-de-bremer/",
    "titulo": "Brasil x França: veja gol de Bremer em amistoso",
    "subtitulo": "Zagueiro diminuiu o placar para a Seleção",
    "categoria": "Seleção Brasileira",
    "data_publicacao": "2026-03-26T18:52:27-03:00",
    "imagem": "https://admin.cnnbrasil.com.br/wp-content/uploads/sites/12/2026/03/selecao_amistoso-e1774556254467.jpg?w=1200&h=630&crop=1",
    "corpo": "Bremer fez o primeiro gol do Brasil contra a França, nesta quinta (26), em amistoso realizado no Gillette Stadium, em Boston, nos Estados Unidos.\nApós cruzamento na área, a bola rebate e Luiz Henrique consegue chutar pro meio da área e o zagueiro brasileiro deixou o placar em 2 a 1.\n\nBremer é o nome da emoção! Brasil diminui diante da França! #futebol #seleocaobrasileira #frança #amistoso pic.twitter.com/AaLl2Fwm39\n— ge (@geglobo) March 26, 2026\n\n\nhttps://stories.cnnbrasil.com.br/esportes/entenda-polemica-do-brasa-no-uniforme-da-selecao-brasileira/\n&nbsp;"
}